CHANGES.rst
LICENSE
MANIFEST.in
README.rst
setup.cfg
setup.py
test.txt
pymiparse/__init__.py
pymiparse/exceptions.py
pymiparse.egg-info/PKG-INFO
pymiparse.egg-info/SOURCES.txt
pymiparse.egg-info/dependency_links.txt
pymiparse.egg-info/top_level.txt